iceye/__init__.py
iceye-0.0.1.dist-info/METADATA
iceye-0.0.1.dist-info/WHEEL
iceye-0.0.1.dist-info/top_level.txt
iceye-0.0.1.dist-info/RECORD
