Metadata-Version: 2.1
Name: iceye
Version: 0.0.1
Summary: A minimal package for ICEYE service access in the future
Home-page: https://github.com/mkorpela/iceye
Author: Mikko Korpela
Author-email: mikko.korpela@gmail.com
License: UNKNOWN
Platform: UNKNOWN
Classifier: Development Status :: 1 - Planning
Classifier: License :: OSI Approved :: MIT License
Classifier: Programming Language :: Python :: 3
Classifier: Programming Language :: Python :: 3.6
Classifier: Programming Language :: Python :: 3.7
Classifier: Programming Language :: Python :: 3.8
Classifier: Programming Language :: Python :: 3.9
Requires-Python: >=3.6
